{
    "params": [
        {
            "kernel": "poly",
            "gamma": "scale",
            "C": 0.5416088662349648
        },
        {
            "kernel": "rbf",
            "gamma": "scale",
            "C": 0.10901182293746411
        },
        {
            "kernel": "rbf",
            "gamma": "auto",
            "C": 1.5333545936438178
        },
        {
            "kernel": "sigmoid",
            "gamma": "auto",
            "C": 7.436573891581514
        },
        {
            "kernel": "poly",
            "gamma": 0.0001,
            "C": 2.357214439157586
        },
        {
            "kernel": "linear",
            "gamma": 0.01,
            "C": 2.3884401068247443
        },
        {
            "kernel": "sigmoid",
            "gamma": 0.0001,
            "C": 4.462055373256671
        },
        {
            "kernel": "poly",
            "gamma": 0.001,
            "C": 4.171813926750545
        },
        {
            "kernel": "sigmoid",
            "gamma": "scale",
            "C": 2.7792949407326324
        },
        {
            "kernel": "sigmoid",
            "gamma": 0.001,
            "C": 10.073216615714875
        },
        {
            "kernel": "linear",
            "gamma": "auto",
            "C": 0.45743987943576825
        },
        {
            "kernel": "linear",
            "gamma": 0.1,
            "C": 0.23218478152948646
        },
        {
            "kernel": "rbf",
            "gamma": "scale",
            "C": 2.357214439157586
        },
        {
            "kernel": "rbf",
            "gamma": 0.0001,
            "C": 10.073216615714875
        },
        {
            "kernel": "linear",
            "gamma": "scale",
            "C": 9.826694296537132
        },
        {
            "kernel": "poly",
            "gamma": "scale",
            "C": 0.5962087468819995
        },
        {
            "kernel": "sigmoid",
            "gamma": 0.01,
            "C": 0.8523528889082909
        },
        {
            "kernel": "rbf",
            "gamma": 0.1,
            "C": 10.225398498678135
        },
        {
            "kernel": "poly",
            "gamma": 0.1,
            "C": 0.45743987943576825
        },
        {
            "kernel": "sigmoid",
            "gamma": 0.001,
            "C": 2.7792949407326324
        },
        {
            "kernel": "linear",
            "gamma": 0.1,
            "C": 4.4728802419738525
        },
        {
            "kernel": "rbf",
            "gamma": 0.0001,
            "C": 0.8801472043212692
        },
        {
            "kernel": "linear",
            "gamma": "auto",
            "C": 4.233817591907997
        },
        {
            "kernel": "linear",
            "gamma": 0.0001,
            "C": 0.06799520598606286
        },
        {
            "kernel": "rbf",
            "gamma": 0.001,
            "C": 1.5333545936438178
        },
        {
            "kernel": "rbf",
            "gamma": 0.001,
            "C": 0.7806413045292133
        },
        {
            "kernel": "rbf",
            "gamma": "auto",
            "C": 4.233817591907997
        },
        {
            "kernel": "poly",
            "gamma": 0.01,
            "C": 2.8412626009906847
        },
        {
            "kernel": "poly",
            "gamma": 0.1,
            "C": 0.06799520598606286
        },
        {
            "kernel": "poly",
            "gamma": 0.1,
            "C": 3.3925419057960284
        },
        {
            "kernel": "poly",
            "gamma": "auto",
            "C": 1.1297395589777577
        },
        {
            "kernel": "rbf",
            "gamma": "auto",
            "C": 1.1335399027174107
        },
        {
            "kernel": "linear",
            "gamma": 0.1,
            "C": 4.233817591907997
        },
        {
            "kernel": "sigmoid",
            "gamma": "auto",
            "C": 4.499786317184287
        },
        {
            "kernel": "poly",
            "gamma": "scale",
            "C": 4.4728802419738525
        },
        {
            "kernel": "linear",
            "gamma": 0.1,
            "C": 3.3925419057960284
        },
        {
            "kernel": "sigmoid",
            "gamma": 0.01,
            "C": 2.7792949407326324
        },
        {
            "kernel": "poly",
            "gamma": 0.1,
            "C": 2.357214439157586
        },
        {
            "kernel": "rbf",
            "gamma": 0.0001,
            "C": 4.462055373256671
        },
        {
            "kernel": "linear",
            "gamma": "auto",
            "C": 2.393864422144914
        },
        {
            "kernel": "rbf",
            "gamma": 0.0001,
            "C": 16.142127891629823
        },
        {
            "kernel": "sigmoid",
            "gamma": 0.0001,
            "C": 1.5333545936438178
        },
        {
            "kernel": "linear",
            "gamma": "auto",
            "C": 2.3884401068247443
        },
        {
            "kernel": "sigmoid",
            "gamma": 0.01,
            "C": 0.06799520598606286
        },
        {
            "kernel": "poly",
            "gamma": 0.001,
            "C": 3.3145132857886623
        },
        {
            "kernel": "poly",
            "gamma": "auto",
            "C": 0.06799520598606286
        },
        {
            "kernel": "poly",
            "gamma": 0.01,
            "C": 0.06799520598606286
        },
        {
            "kernel": "sigmoid",
            "gamma": 0.1,
            "C": 0.15006070806052763
        },
        {
            "kernel": "sigmoid",
            "gamma": 0.01,
            "C": 0.23218478152948646
        },
        {
            "kernel": "sigmoid",
            "gamma": "scale",
            "C": 9.826694296537132
        }
    ],
    "mean_test_score": [
        0.5790971094100618,
        0.6640651567922227,
        0.7778227972920868,
        0.7191722028027281,
        0.5424827594925506,
        0.6882423215741801,
        0.7550684879553484,
        0.7675126261828157,
        0.7397900166242106,
        0.6789877562372395,
        0.6988982509813341,
        0.7056528637257194,
        0.7806672439839952,
        0.77711042142058,
        0.6896626486223396,
        0.5808745725428721,
        0.5755554572290033,
        0.5453240456881348,
        0.748318932005082,
        0.7067223756818771,
        0.681841684418121,
        0.7390789049512334,
        0.6814870767305299,
        0.7312484592580418,
        0.7813783556569723,
        0.7732027837651625,
        0.7767551816337237,
        0.748318932005082,
        0.748318932005082,
        0.748318932005082,
        0.5979387242972637,
        0.7746193182177329,
        0.6814870767305299,
        0.7216614097077805,
        0.7301840040960033,
        0.6846861311100295,
        0.581596429903352,
        0.748318932005082,
        0.7774625007111116,
        0.6882423215741801,
        0.7792488132336303,
        0.7394316163410302,
        0.6882423215741801,
        0.5883529389455321,
        0.757912934647257,
        0.5474592770048609,
        0.7675195792747294,
        0.5183125478025069,
        0.5933225033659286,
        0.7131211165401414
    ],
    "std_test_score": [
        0.00739001424130082,
        0.018396556930881332,
        0.009541445838619607,
        0.018537322607588988,
        0.0030667326244471307,
        0.02088804897503836,
        0.007137529991560897,
        0.013884841080675408,
        0.01606496715165422,
        0.01235401660070611,
        0.011313588851579456,
        0.006384734017108115,
        0.012837019539513555,
        0.00899985645864228,
        0.01701140810283131,
        0.008795149284867075,
        0.027994644383302313,
        0.006576418104547541,
        0.01736737052530249,
        0.008877338180451118,
        0.016229408467302812,
        0.017087283983103538,
        0.018037458804502887,
        0.01095361195803587,
        0.013725455660986804,
        0.011531429870835403,
        0.012617481767887809,
        0.01736737052530249,
        0.01736737052530249,
        0.01736737052530249,
        0.012919027123507808,
        0.007774230051090802,
        0.018037458804502887,
        0.019926736987424944,
        0.014412909990640592,
        0.01777171306927232,
        0.027147862774852222,
        0.01736737052530249,
        0.01130237964983494,
        0.02112832729954854,
        0.013952184332769374,
        0.013968187507389257,
        0.02088804897503836,
        0.021534809189321737,
        0.012466437016546822,
        0.002689195434068123,
        0.01694440221220375,
        0.011697251697425335,
        0.025290054955871687,
        0.010113770438868781
    ],
    "rank_test_score": [
        45,
        39,
        4,
        25,
        49,
        32,
        13,
        11,
        19,
        38,
        29,
        28,
        2,
        6,
        30,
        44,
        46,
        48,
        16,
        27,
        35,
        21,
        36,
        22,
        1,
        9,
        7,
        16,
        16,
        16,
        40,
        8,
        36,
        24,
        23,
        34,
        43,
        16,
        5,
        32,
        3,
        20,
        32,
        42,
        12,
        47,
        10,
        50,
        41,
        26
    ]
}