{
    "params": [
        {
            "penalty": "l1",
            "loss": "squared_error",
            "alpha": 0.08889688775863265
        },
        {
            "penalty": "elasticnet",
            "loss": "squared_error",
            "alpha": 11.965532514844739
        },
        {
            "penalty": "l2",
            "loss": "squared_error",
            "alpha": 0.05228467633389851
        },
        {
            "penalty": "l2",
            "loss": "perceptron",
            "alpha": 17.859921588309284
        },
        {
            "penalty": "l2",
            "loss": "log_loss",
            "alpha": 17.15402544817722
        },
        {
            "penalty": "elasticnet",
            "loss": "squared_hinge",
            "alpha": 0.19987544509621577
        },
        {
            "penalty": "elasticnet",
            "loss": "squared_hinge",
            "alpha": 0.3261713383243039
        },
        {
            "penalty": "elasticnet",
            "loss": "hinge",
            "alpha": 3.8408477939616237
        },
        {
            "penalty": "l2",
            "loss": "hinge",
            "alpha": 0.22918114928198755
        },
        {
            "penalty": "elasticnet",
            "loss": "perceptron",
            "alpha": 0.22918114928198755
        },
        {
            "penalty": "l1",
            "loss": "perceptron",
            "alpha": 0.18912738442838414
        },
        {
            "penalty": "elasticnet",
            "loss": "squared_hinge",
            "alpha": 3.059519006509734
        },
        {
            "penalty": "l2",
            "loss": "squared_hinge",
            "alpha": 0.5758632526520523
        },
        {
            "penalty": "l2",
            "loss": "perceptron",
            "alpha": 3.8408477939616237
        },
        {
            "penalty": "l2",
            "loss": "squared_hinge",
            "alpha": 15.476965642941254
        },
        {
            "penalty": "elasticnet",
            "loss": "perceptron",
            "alpha": 17.859921588309284
        },
        {
            "penalty": "l2",
            "loss": "modified_huber",
            "alpha": 14.282011288456294
        },
        {
            "penalty": "elasticnet",
            "loss": "modified_huber",
            "alpha": 0.17141238619804244
        },
        {
            "penalty": "l2",
            "loss": "squared_error",
            "alpha": 0.1447540827215924
        },
        {
            "penalty": "l1",
            "loss": "perceptron",
            "alpha": 0.08889688775863265
        },
        {
            "penalty": "l1",
            "loss": "perceptron",
            "alpha": 0.23631441381660329
        },
        {
            "penalty": "l2",
            "loss": "log_loss",
            "alpha": 3.9217169012554853
        },
        {
            "penalty": "l1",
            "loss": "log_loss",
            "alpha": 0.07480715917223646
        },
        {
            "penalty": "l2",
            "loss": "squared_hinge",
            "alpha": 19.240283542591296
        },
        {
            "penalty": "elasticnet",
            "loss": "hinge",
            "alpha": 0.12934008735136457
        },
        {
            "penalty": "elasticnet",
            "loss": "hinge",
            "alpha": 1.1017314344621032
        },
        {
            "penalty": "l2",
            "loss": "perceptron",
            "alpha": 0.09851410148401107
        },
        {
            "penalty": "l2",
            "loss": "squared_hinge",
            "alpha": 0.6831449773177585
        },
        {
            "penalty": "l1",
            "loss": "squared_hinge",
            "alpha": 1.9633539439629948
        },
        {
            "penalty": "l2",
            "loss": "hinge",
            "alpha": 3.059519006509734
        },
        {
            "penalty": "elasticnet",
            "loss": "modified_huber",
            "alpha": 0.1734534202977403
        },
        {
            "penalty": "l2",
            "loss": "hinge",
            "alpha": 0.5624434440810435
        },
        {
            "penalty": "l1",
            "loss": "squared_hinge",
            "alpha": 0.3261713383243039
        },
        {
            "penalty": "l2",
            "loss": "squared_hinge",
            "alpha": 3.059519006509734
        },
        {
            "penalty": "l2",
            "loss": "log_loss",
            "alpha": 0.6338898961982831
        },
        {
            "penalty": "l2",
            "loss": "squared_hinge",
            "alpha": 1.4460965493581461
        },
        {
            "penalty": "elasticnet",
            "loss": "log_loss",
            "alpha": 0.09851410148401107
        },
        {
            "penalty": "l1",
            "loss": "perceptron",
            "alpha": 17.859921588309284
        },
        {
            "penalty": "elasticnet",
            "loss": "squared_error",
            "alpha": 0.17141238619804244
        },
        {
            "penalty": "elasticnet",
            "loss": "squared_hinge",
            "alpha": 0.23631441381660329
        },
        {
            "penalty": "l2",
            "loss": "squared_hinge",
            "alpha": 0.08889688775863265
        },
        {
            "penalty": "elasticnet",
            "loss": "log_loss",
            "alpha": 0.37219503166061013
        },
        {
            "penalty": "l1",
            "loss": "squared_hinge",
            "alpha": 0.08553432759741263
        },
        {
            "penalty": "l2",
            "loss": "modified_huber",
            "alpha": 3.9217169012554853
        },
        {
            "penalty": "l1",
            "loss": "log_loss",
            "alpha": 1.9633539439629948
        },
        {
            "penalty": "l1",
            "loss": "perceptron",
            "alpha": 0.6338898961982831
        },
        {
            "penalty": "elasticnet",
            "loss": "squared_error",
            "alpha": 0.23631441381660329
        },
        {
            "penalty": "l2",
            "loss": "squared_error",
            "alpha": 0.1218330318206921
        },
        {
            "penalty": "elasticnet",
            "loss": "modified_huber",
            "alpha": 7.372977261137474
        },
        {
            "penalty": "l1",
            "loss": "log_loss",
            "alpha": 0.6831449773177585
        }
    ],
    "mean_test_score": [
        0.5325263561242879,
        0.4627546759161187,
        0.4552303692064462,
        0.8452307392970217,
        0.8837147534933658,
        0.8745137016359351,
        0.8515088714538006,
        0.8839211996709977,
        0.8805293913018974,
        0.8509811901356207,
        0.8454328409331137,
        0.8531624587600156,
        0.8558455675956521,
        0.8676428374579153,
        0.8763421056396801,
        0.8845997396493255,
        0.8617449809781708,
        0.8797035804980272,
        0.49327371468434605,
        0.8837144838621592,
        0.8791725766275581,
        0.882653232828156,
        0.8711807424521417,
        0.875251121241803,
        0.8507157599570782,
        0.8864870841650768,
        0.8682616454261785,
        0.8673763070100939,
        0.8663152125361464,
        0.8839801793230178,
        0.8779936315718311,
        0.8851010232025918,
        0.8637196947026731,
        0.8428704312024887,
        0.8839800662518666,
        0.8483544211755127,
        0.8826238082355025,
        0.7934759032982464,
        0.47066317230421306,
        0.853249214775216,
        0.854222966133755,
        0.886929409810775,
        0.8713573943814336,
        0.8884039098090571,
        0.8839211996709977,
        0.8670823698547789,
        0.5775570508103918,
        0.5225502841543262,
        0.8847768743054552,
        0.8851303434218749
    ],
    "std_test_score": [
        0.1781588503927269,
        0.19010048875605623,
        0.1933328358776391,
        0.07981874495746613,
        0.00031903387116711466,
        0.01162943211028242,
        0.02258381199944332,
        5.608171510535254e-05,
        0.006815467404080909,
        0.03413622986137739,
        0.039535830327151446,
        0.02623061644610368,
        0.024931349298871947,
        0.02364570146703676,
        0.00605947006024289,
        0.005282584553808169,
        0.047454431263052016,
        0.004746711542192155,
        0.12227300532429204,
        0.0049675470979427695,
        0.011945783896027844,
        0.004143164634807672,
        0.014455856977940294,
        0.0063626480353466235,
        0.046789345298799113,
        0.003473813696017293,
        0.012508630884551026,
        0.01508966308551782,
        0.007057169726145331,
        0.00014610135207640396,
        0.004740582568695756,
        0.0033768547100653415,
        0.011748591153355118,
        0.029967292946636942,
        0.001755881089168288,
        0.024789526142004244,
        0.0044253396631642634,
        0.18094614998259811,
        0.12800504336119672,
        0.013508593829334222,
        0.02163117695010763,
        0.003494024698721116,
        0.008426674804550949,
        0.0019971475668977812,
        5.608171510535254e-05,
        0.029241406928892568,
        0.15500229251231443,
        0.21076520224191336,
        0.008036804841440736,
        0.0016239564065523666
    ],
    "rank_test_score": [
        45,
        49,
        50,
        41,
        12,
        22,
        36,
        10,
        16,
        37,
        40,
        35,
        32,
        26,
        20,
        7,
        31,
        17,
        47,
        13,
        18,
        14,
        24,
        21,
        38,
        3,
        25,
        27,
        29,
        8,
        19,
        5,
        30,
        42,
        9,
        39,
        15,
        43,
        48,
        34,
        33,
        2,
        23,
        1,
        10,
        28,
        44,
        46,
        6,
        4
    ]
}