{
    "params": [
        {
            "var_smoothing": 1e-05
        },
        {
            "var_smoothing": 1e-06
        },
        {
            "var_smoothing": 1e-07
        },
        {
            "var_smoothing": 1e-08
        },
        {
            "var_smoothing": 1e-09
        },
        {
            "var_smoothing": 1e-10
        },
        {
            "var_smoothing": 1e-11
        },
        {
            "var_smoothing": 1e-12
        }
    ],
    "mean_test_score": [
        0.6394095238095238,
        0.6090857142857142,
        0.5855428571428571,
        0.5671428571428571,
        0.5522095238095238,
        0.5399619047619048,
        0.53,
        0.5209142857142857
    ],
    "std_test_score": [
        0.0077700278849778415,
        0.008148641777117915,
        0.007295611080854271,
        0.006812287151598049,
        0.0060060136152430945,
        0.005469552913200032,
        0.004734013556565066,
        0.004676801434242081
    ],
    "rank_test_score": [
        8,
        7,
        6,
        5,
        4,
        3,
        2,
        1
    ]
}