{
    "params": [
        {
            "kernel": "poly",
            "gamma": "scale",
            "C": 13.25091075547948
        },
        {
            "kernel": "rbf",
            "gamma": "scale",
            "C": 2.281310852634895
        },
        {
            "kernel": "rbf",
            "gamma": "auto",
            "C": 0.22297692409453163
        },
        {
            "kernel": "sigmoid",
            "gamma": "auto",
            "C": 0.08438527119363887
        },
        {
            "kernel": "poly",
            "gamma": 0.0001,
            "C": 0.5660567902260264
        },
        {
            "kernel": "linear",
            "gamma": 0.01,
            "C": 3.7173816584054573
        },
        {
            "kernel": "sigmoid",
            "gamma": 0.0001,
            "C": 0.05513632574225919
        },
        {
            "kernel": "poly",
            "gamma": 0.001,
            "C": 8.45724106132167
        },
        {
            "kernel": "sigmoid",
            "gamma": "scale",
            "C": 0.06371416747509823
        },
        {
            "kernel": "sigmoid",
            "gamma": 0.001,
            "C": 0.8735308029488069
        },
        {
            "kernel": "linear",
            "gamma": "auto",
            "C": 4.74746250701382
        },
        {
            "kernel": "linear",
            "gamma": 0.1,
            "C": 0.9021947438550793
        },
        {
            "kernel": "rbf",
            "gamma": "scale",
            "C": 0.5660567902260264
        },
        {
            "kernel": "rbf",
            "gamma": 0.0001,
            "C": 0.8735308029488069
        },
        {
            "kernel": "linear",
            "gamma": "scale",
            "C": 0.6788357949777423
        },
        {
            "kernel": "poly",
            "gamma": "scale",
            "C": 0.05944168785619398
        },
        {
            "kernel": "sigmoid",
            "gamma": 0.01,
            "C": 12.160734988099556
        },
        {
            "kernel": "rbf",
            "gamma": 0.1,
            "C": 0.39009870141605446
        },
        {
            "kernel": "poly",
            "gamma": 0.1,
            "C": 4.74746250701382
        },
        {
            "kernel": "sigmoid",
            "gamma": 0.001,
            "C": 0.06371416747509823
        },
        {
            "kernel": "linear",
            "gamma": 0.1,
            "C": 0.2559835683542798
        },
        {
            "kernel": "rbf",
            "gamma": 0.0001,
            "C": 15.965703814983183
        },
        {
            "kernel": "linear",
            "gamma": "auto",
            "C": 3.4354562377106936
        },
        {
            "kernel": "linear",
            "gamma": 0.0001,
            "C": 0.23781968331186176
        },
        {
            "kernel": "rbf",
            "gamma": 0.001,
            "C": 0.22297692409453163
        },
        {
            "kernel": "rbf",
            "gamma": 0.001,
            "C": 0.07853252279023633
        },
        {
            "kernel": "rbf",
            "gamma": "auto",
            "C": 3.4354562377106936
        },
        {
            "kernel": "poly",
            "gamma": 0.01,
            "C": 0.14760485328324613
        },
        {
            "kernel": "poly",
            "gamma": 0.1,
            "C": 0.23781968331186176
        },
        {
            "kernel": "poly",
            "gamma": 0.1,
            "C": 2.6785670798926984
        },
        {
            "kernel": "poly",
            "gamma": "auto",
            "C": 4.544565110361567
        },
        {
            "kernel": "rbf",
            "gamma": "auto",
            "C": 0.08458243981989268
        },
        {
            "kernel": "linear",
            "gamma": 0.1,
            "C": 3.4354562377106936
        },
        {
            "kernel": "sigmoid",
            "gamma": "auto",
            "C": 1.6477572824300402
        },
        {
            "kernel": "poly",
            "gamma": "scale",
            "C": 0.2559835683542798
        },
        {
            "kernel": "linear",
            "gamma": 0.1,
            "C": 2.6785670798926984
        },
        {
            "kernel": "sigmoid",
            "gamma": 0.01,
            "C": 0.06371416747509823
        },
        {
            "kernel": "poly",
            "gamma": 0.1,
            "C": 0.5660567902260264
        },
        {
            "kernel": "rbf",
            "gamma": 0.0001,
            "C": 0.05513632574225919
        },
        {
            "kernel": "linear",
            "gamma": "auto",
            "C": 3.5134152261662446
        },
        {
            "kernel": "rbf",
            "gamma": 0.0001,
            "C": 5.828683763285889
        },
        {
            "kernel": "sigmoid",
            "gamma": 0.0001,
            "C": 0.22297692409453163
        },
        {
            "kernel": "linear",
            "gamma": "auto",
            "C": 3.7173816584054573
        },
        {
            "kernel": "sigmoid",
            "gamma": 0.01,
            "C": 0.23781968331186176
        },
        {
            "kernel": "poly",
            "gamma": 0.001,
            "C": 1.7276787343758875
        },
        {
            "kernel": "poly",
            "gamma": "auto",
            "C": 0.23781968331186176
        },
        {
            "kernel": "poly",
            "gamma": 0.01,
            "C": 0.23781968331186176
        },
        {
            "kernel": "sigmoid",
            "gamma": 0.1,
            "C": 0.26283234921523285
        },
        {
            "kernel": "sigmoid",
            "gamma": 0.01,
            "C": 0.9021947438550793
        },
        {
            "kernel": "sigmoid",
            "gamma": "scale",
            "C": 0.6788357949777423
        }
    ],
    "mean_test_score": [
        0.47102803738317756,
        0.5271028037383176,
        0.5289719626168223,
        0.5289719626168223,
        0.5289719626168223,
        0.5121495327102803,
        0.5289719626168223,
        0.5289719626168223,
        0.5289719626168223,
        0.5289719626168223,
        0.5140186915887849,
        0.5177570093457943,
        0.5289719626168223,
        0.5289719626168223,
        0.5177570093457943,
        0.5271028037383176,
        0.502803738317757,
        0.5289719626168223,
        0.4710280373831776,
        0.5289719626168223,
        0.5196261682242991,
        0.5289719626168223,
        0.5140186915887849,
        0.5196261682242991,
        0.5289719626168223,
        0.5289719626168223,
        0.5158878504672897,
        0.5289719626168223,
        0.508411214953271,
        0.47289719626168225,
        0.4672897196261682,
        0.5289719626168223,
        0.5140186915887849,
        0.5233644859813082,
        0.5271028037383177,
        0.5140186915887849,
        0.5289719626168223,
        0.4934579439252336,
        0.5289719626168223,
        0.5140186915887849,
        0.5289719626168223,
        0.5289719626168223,
        0.5121495327102803,
        0.5289719626168223,
        0.5289719626168223,
        0.5271028037383176,
        0.5289719626168223,
        0.5289719626168223,
        0.5289719626168223,
        0.5289719626168223
    ],
    "std_test_score": [
        0.03766250781235491,
        0.011214953271028038,
        0.004578485500529305,
        0.004578485500529305,
        0.004578485500529305,
        0.02669692870483306,
        0.004578485500529305,
        0.004578485500529305,
        0.004578485500529305,
        0.004578485500529305,
        0.023643197459202812,
        0.02549192840558102,
        0.004578485500529305,
        0.004578485500529305,
        0.02549192840558102,
        0.007476635514018694,
        0.019957155611273456,
        0.004578485500529305,
        0.022585132660924438,
        0.004578485500529305,
        0.02179795100876746,
        0.004578485500529305,
        0.023643197459202812,
        0.02179795100876746,
        0.004578485500529305,
        0.004578485500529305,
        0.025354504609814064,
        0.004578485500529305,
        0.0357591148966523,
        0.03766250781235492,
        0.03875970346416396,
        0.004578485500529305,
        0.023643197459202812,
        0.01182159872960142,
        0.020981256374433297,
        0.023643197459202812,
        0.004578485500529305,
        0.033121579713400635,
        0.004578485500529305,
        0.023643197459202812,
        0.004578485500529305,
        0.004578485500529305,
        0.02669692870483306,
        0.004578485500529305,
        0.004578485500529305,
        0.0357591148966523,
        0.004578485500529305,
        0.004578485500529305,
        0.004578485500529305,
        0.004578485500529305
    ],
    "rank_test_score": [
        2,
        21,
        25,
        25,
        25,
        8,
        25,
        25,
        25,
        25,
        10,
        16,
        25,
        25,
        16,
        21,
        6,
        25,
        3,
        25,
        18,
        25,
        10,
        18,
        25,
        25,
        15,
        25,
        7,
        4,
        1,
        25,
        10,
        20,
        24,
        10,
        25,
        5,
        25,
        10,
        25,
        25,
        8,
        25,
        25,
        21,
        25,
        25,
        25,
        25
    ]
}