{
    "params": [
        {
            "penalty": "l1",
            "loss": "squared_error",
            "alpha": 14.026130569554699
        },
        {
            "penalty": "elasticnet",
            "loss": "squared_error",
            "alpha": 0.06271347737148947
        },
        {
            "penalty": "l2",
            "loss": "squared_error",
            "alpha": 7.098564075304714
        },
        {
            "penalty": "l2",
            "loss": "perceptron",
            "alpha": 3.707418052719055
        },
        {
            "penalty": "l2",
            "loss": "log_loss",
            "alpha": 0.519206701380893
        },
        {
            "penalty": "elasticnet",
            "loss": "squared_hinge",
            "alpha": 0.10555927116063242
        },
        {
            "penalty": "elasticnet",
            "loss": "squared_hinge",
            "alpha": 4.153469806991638
        },
        {
            "penalty": "elasticnet",
            "loss": "hinge",
            "alpha": 0.3010153030428397
        },
        {
            "penalty": "l2",
            "loss": "hinge",
            "alpha": 0.3938533772339976
        },
        {
            "penalty": "elasticnet",
            "loss": "perceptron",
            "alpha": 0.3938533772339976
        },
        {
            "penalty": "l1",
            "loss": "perceptron",
            "alpha": 0.5816898445290858
        },
        {
            "penalty": "elasticnet",
            "loss": "squared_hinge",
            "alpha": 0.3452325723755338
        },
        {
            "penalty": "l2",
            "loss": "squared_hinge",
            "alpha": 10.450037056765103
        },
        {
            "penalty": "l2",
            "loss": "perceptron",
            "alpha": 0.3010153030428397
        },
        {
            "penalty": "l2",
            "loss": "squared_hinge",
            "alpha": 0.24542854367513983
        },
        {
            "penalty": "elasticnet",
            "loss": "perceptron",
            "alpha": 3.707418052719055
        },
        {
            "penalty": "l2",
            "loss": "modified_huber",
            "alpha": 0.08677118611624128
        },
        {
            "penalty": "elasticnet",
            "loss": "modified_huber",
            "alpha": 0.1423996605193735
        },
        {
            "penalty": "l2",
            "loss": "squared_error",
            "alpha": 2.3856717796131113
        },
        {
            "penalty": "l1",
            "loss": "perceptron",
            "alpha": 14.026130569554699
        },
        {
            "penalty": "l1",
            "loss": "perceptron",
            "alpha": 0.07487869088187984
        },
        {
            "penalty": "l2",
            "loss": "log_loss",
            "alpha": 3.669350182233405
        },
        {
            "penalty": "l1",
            "loss": "log_loss",
            "alpha": 0.25039520213167776
        },
        {
            "penalty": "l2",
            "loss": "squared_hinge",
            "alpha": 0.7315291681283355
        },
        {
            "penalty": "elasticnet",
            "loss": "hinge",
            "alpha": 1.172864249637792
        },
        {
            "penalty": "elasticnet",
            "loss": "hinge",
            "alpha": 0.10472935383499736
        },
        {
            "penalty": "l2",
            "loss": "perceptron",
            "alpha": 0.1453811696739085
        },
        {
            "penalty": "l2",
            "loss": "squared_hinge",
            "alpha": 1.995818437351671
        },
        {
            "penalty": "l1",
            "loss": "squared_hinge",
            "alpha": 2.59288398067607
        },
        {
            "penalty": "l2",
            "loss": "hinge",
            "alpha": 0.3452325723755338
        },
        {
            "penalty": "elasticnet",
            "loss": "modified_huber",
            "alpha": 15.64942560231748
        },
        {
            "penalty": "l2",
            "loss": "hinge",
            "alpha": 3.4668912842393422
        },
        {
            "penalty": "l1",
            "loss": "squared_hinge",
            "alpha": 4.153469806991638
        },
        {
            "penalty": "l2",
            "loss": "squared_hinge",
            "alpha": 0.3452325723755338
        },
        {
            "penalty": "l2",
            "loss": "log_loss",
            "alpha": 0.2654281423008321
        },
        {
            "penalty": "l2",
            "loss": "squared_hinge",
            "alpha": 9.18222521329647
        },
        {
            "penalty": "elasticnet",
            "loss": "log_loss",
            "alpha": 0.1453811696739085
        },
        {
            "penalty": "l1",
            "loss": "perceptron",
            "alpha": 3.707418052719055
        },
        {
            "penalty": "elasticnet",
            "loss": "squared_error",
            "alpha": 0.1423996605193735
        },
        {
            "penalty": "elasticnet",
            "loss": "squared_hinge",
            "alpha": 0.07487869088187984
        },
        {
            "penalty": "l2",
            "loss": "squared_hinge",
            "alpha": 14.026130569554699
        },
        {
            "penalty": "elasticnet",
            "loss": "log_loss",
            "alpha": 9.691267541640668
        },
        {
            "penalty": "l1",
            "loss": "squared_hinge",
            "alpha": 0.28207901351604986
        },
        {
            "penalty": "l2",
            "loss": "modified_huber",
            "alpha": 3.669350182233405
        },
        {
            "penalty": "l1",
            "loss": "log_loss",
            "alpha": 2.59288398067607
        },
        {
            "penalty": "l1",
            "loss": "perceptron",
            "alpha": 0.2654281423008321
        },
        {
            "penalty": "elasticnet",
            "loss": "squared_error",
            "alpha": 0.07487869088187984
        },
        {
            "penalty": "l2",
            "loss": "squared_error",
            "alpha": 1.280824122168311
        },
        {
            "penalty": "elasticnet",
            "loss": "modified_huber",
            "alpha": 0.13041697305709207
        },
        {
            "penalty": "l1",
            "loss": "log_loss",
            "alpha": 1.995818437351671
        }
    ],
    "mean_test_score": [
        0.10853333333333333,
        0.10706666666666667,
        0.10085714285714287,
        0.8719047619047618,
        0.8981523809523809,
        0.8700761904761904,
        0.8409714285714285,
        0.8853333333333333,
        0.8948952380952381,
        0.849047619047619,
        0.6804190476190477,
        0.8415619047619047,
        0.8271809523809524,
        0.8762095238095238,
        0.8661142857142858,
        0.7408952380952382,
        0.8654666666666667,
        0.8687619047619048,
        0.10041904761904763,
        0.17097142857142858,
        0.8439619047619047,
        0.9070666666666668,
        0.8126095238095239,
        0.8237333333333334,
        0.8824,
        0.8751809523809524,
        0.8737904761904762,
        0.8334666666666667,
        0.8201904761904762
    ],
    "std_test_score": [
        0.009151702070852768,
        0.020156341315776913,
        0.009245456075818356,
        0.015043157867929724,
        0.005232585847219908,
        0.00672448398074202,
        0.014632539144456731,
        0.007556169109408343,
        0.01000999047437369,
        0.014555422270079178,
        0.013803755774041658,
        0.022808010686465454,
        0.016341769305564215,
        0.0124767575298252,
        0.02038730653062579,
        0.057120586136210294,
        0.021359473780536018,
        0.005706979456110871,
        0.0224949558467838,
        0.05970434792372942,
        0.0061723103426501785,
        0.0032478285088156683,
        0.007316765452667054,
        0.01881586632065675,
        0.005382224881143681,
        0.011458152193991863,
        0.005674592296581884,
        0.017084195929773605,
        0.018811199443145462
    ],
    "rank_test_score": [
        4,
        3,
        2,
        21,
        28,
        20,
        13,
        26,
        27,
        16,
        6,
        14,
        11,
        24,
        18,
        7,
        17,
        19,
        1,
        5,
        15,
        29,
        8,
        10,
        25,
        23,
        22,
        12,
        9
    ]
}