{
    "params": [
        {
            "kernel": "poly",
            "gamma": "scale",
            "C": 1.0550386079095682
        },
        {
            "kernel": "rbf",
            "gamma": "scale",
            "C": 5.964976797875029
        },
        {
            "kernel": "rbf",
            "gamma": "auto",
            "C": 4.915817514074422
        },
        {
            "kernel": "sigmoid",
            "gamma": "auto",
            "C": 1.068432392052895
        },
        {
            "kernel": "poly",
            "gamma": 0.0001,
            "C": 2.2037193876589045
        },
        {
            "kernel": "linear",
            "gamma": 0.01,
            "C": 3.398244554295878
        },
        {
            "kernel": "sigmoid",
            "gamma": 0.0001,
            "C": 0.3065141328147723
        },
        {
            "kernel": "poly",
            "gamma": 0.001,
            "C": 2.32191295668694
        },
        {
            "kernel": "sigmoid",
            "gamma": "scale",
            "C": 8.361720276664057
        },
        {
            "kernel": "sigmoid",
            "gamma": 0.001,
            "C": 2.649402352380206
        },
        {
            "kernel": "linear",
            "gamma": "auto",
            "C": 0.3064247371451643
        },
        {
            "kernel": "linear",
            "gamma": 0.1,
            "C": 0.1681638352293129
        },
        {
            "kernel": "rbf",
            "gamma": "scale",
            "C": 2.2037193876589045
        },
        {
            "kernel": "rbf",
            "gamma": 0.0001,
            "C": 2.649402352380206
        },
        {
            "kernel": "linear",
            "gamma": "scale",
            "C": 0.1610001970358805
        },
        {
            "kernel": "poly",
            "gamma": "scale",
            "C": 0.35116637809495543
        },
        {
            "kernel": "sigmoid",
            "gamma": 0.01,
            "C": 0.3704641705645896
        },
        {
            "kernel": "rbf",
            "gamma": 0.1,
            "C": 0.28240223573957324
        },
        {
            "kernel": "poly",
            "gamma": 0.1,
            "C": 0.3064247371451643
        },
        {
            "kernel": "sigmoid",
            "gamma": 0.001,
            "C": 8.361720276664057
        },
        {
            "kernel": "linear",
            "gamma": 0.1,
            "C": 11.180254996967646
        },
        {
            "kernel": "rbf",
            "gamma": 0.0001,
            "C": 0.6271525966424022
        },
        {
            "kernel": "linear",
            "gamma": "auto",
            "C": 0.14111636937756328
        },
        {
            "kernel": "linear",
            "gamma": 0.0001,
            "C": 0.06727163723554867
        },
        {
            "kernel": "rbf",
            "gamma": 0.001,
            "C": 4.915817514074422
        },
        {
            "kernel": "rbf",
            "gamma": 0.001,
            "C": 0.06288581733107404
        },
        {
            "kernel": "rbf",
            "gamma": "auto",
            "C": 0.14111636937756328
        },
        {
            "kernel": "poly",
            "gamma": 0.01,
            "C": 2.444421762429515
        },
        {
            "kernel": "poly",
            "gamma": 0.1,
            "C": 0.06727163723554867
        },
        {
            "kernel": "poly",
            "gamma": 0.1,
            "C": 0.1635616526607615
        },
        {
            "kernel": "poly",
            "gamma": "auto",
            "C": 1.1641139972499233
        },
        {
            "kernel": "rbf",
            "gamma": "auto",
            "C": 8.48760733037006
        },
        {
            "kernel": "linear",
            "gamma": 0.1,
            "C": 0.14111636937756328
        },
        {
            "kernel": "sigmoid",
            "gamma": "auto",
            "C": 0.33446435500167904
        },
        {
            "kernel": "poly",
            "gamma": "scale",
            "C": 11.180254996967646
        },
        {
            "kernel": "linear",
            "gamma": 0.1,
            "C": 0.1635616526607615
        },
        {
            "kernel": "sigmoid",
            "gamma": 0.01,
            "C": 8.361720276664057
        },
        {
            "kernel": "poly",
            "gamma": 0.1,
            "C": 2.2037193876589045
        },
        {
            "kernel": "rbf",
            "gamma": 0.0001,
            "C": 0.3065141328147723
        },
        {
            "kernel": "linear",
            "gamma": "auto",
            "C": 0.06239698080339594
        },
        {
            "kernel": "rbf",
            "gamma": 0.0001,
            "C": 16.030363726130425
        },
        {
            "kernel": "sigmoid",
            "gamma": 0.0001,
            "C": 4.915817514074422
        },
        {
            "kernel": "linear",
            "gamma": "auto",
            "C": 3.398244554295878
        },
        {
            "kernel": "sigmoid",
            "gamma": 0.01,
            "C": 0.06727163723554867
        },
        {
            "kernel": "poly",
            "gamma": 0.001,
            "C": 18.486346971816552
        },
        {
            "kernel": "poly",
            "gamma": "auto",
            "C": 0.06727163723554867
        },
        {
            "kernel": "poly",
            "gamma": 0.01,
            "C": 0.06727163723554867
        },
        {
            "kernel": "sigmoid",
            "gamma": 0.1,
            "C": 0.9923110836635749
        },
        {
            "kernel": "sigmoid",
            "gamma": 0.01,
            "C": 0.1681638352293129
        },
        {
            "kernel": "sigmoid",
            "gamma": "scale",
            "C": 0.1610001970358805
        }
    ],
    "mean_test_score": [
        0.6906666666666667,
        0.6906666666666667,
        0.6786666666666668,
        0.696,
        0.696,
        0.7226666666666667,
        0.696,
        0.7,
        0.5933333333333334,
        0.6039999999999999,
        0.712,
        0.7133333333333333,
        0.6906666666666667,
        0.696,
        0.7186666666666667,
        0.6906666666666667,
        0.696,
        0.6946666666666668,
        0.6839999999999999,
        0.5973333333333333,
        0.7253333333333334,
        0.696,
        0.72,
        0.692,
        0.7,
        0.696,
        0.696,
        0.704,
        0.6866666666666668,
        0.708,
        0.7013333333333334,
        0.6813333333333333,
        0.72,
        0.696,
        0.6986666666666667,
        0.7173333333333334,
        0.696,
        0.6506666666666667,
        0.696,
        0.6906666666666667,
        0.6906666666666667,
        0.696,
        0.7226666666666667,
        0.696,
        0.6933333333333334,
        0.7013333333333334
    ],
    "std_test_score": [
        0.01236482466066094,
        0.01236482466066094,
        0.0264659109883723,
        0.003265986323710871,
        0.003265986323710871,
        0.04706496691926078,
        0.003265986323710871,
        0.013984117975602027,
        0.02108185106778922,
        0.0392371705854991,
        0.04389887368841156,
        0.042583251793790175,
        0.01236482466066094,
        0.003265986323710871,
        0.038273866918419545,
        0.01236482466066094,
        0.003265986323710871,
        0.008844332774281042,
        0.041867515914953565,
        0.03832028763519975,
        0.04203702072115854,
        0.003265986323710871,
        0.03577708763999663,
        0.013597385369580767,
        0.0157762127549323,
        0.003265986323710871,
        0.003265986323710871,
        0.05425863986500214,
        0.05448751131120683,
        0.035125172992852005,
        0.04978174587358524,
        0.032496153618543834,
        0.03577708763999663,
        0.003265986323710871,
        0.016546231527987832,
        0.04079215610874227,
        0.003265986323710871,
        0.05744175794276803,
        0.003265986323710871,
        0.015549205052920774,
        0.01236482466066094,
        0.003265986323710871,
        0.04706496691926078,
        0.003265986323710871,
        0.015202339001321862,
        0.04568491119736483
    ],
    "rank_test_score": [
        9,
        9,
        5,
        18,
        18,
        44,
        18,
        32,
        1,
        3,
        38,
        39,
        9,
        18,
        41,
        9,
        18,
        17,
        7,
        2,
        46,
        18,
        42,
        15,
        32,
        18,
        18,
        36,
        8,
        37,
        34,
        6,
        42,
        18,
        31,
        40,
        18,
        4,
        18,
        9,
        9,
        18,
        44,
        18,
        16,
        34
    ]
}