{
    "params": [
        {
            "C": 1.0976270078546495,
            "gamma": 0.1,
            "kernel": "linear"
        },
        {
            "C": 1.2055267521432877,
            "gamma": 0.001,
            "kernel": "sigmoid"
        },
        {
            "C": 0.8473095986778094,
            "gamma": 0.1,
            "kernel": "poly"
        },
        {
            "C": 0.875174422525385,
            "gamma": "scale",
            "kernel": "linear"
        },
        {
            "C": 0.5453125891602264,
            "gamma": "auto",
            "kernel": "poly"
        },
        {
            "C": 1.6243374575509864,
            "gamma": "scale",
            "kernel": "rbf"
        },
        {
            "C": 1.851193276585322,
            "gamma": 0.1,
            "kernel": "linear"
        },
        {
            "C": 0.17425859940308142,
            "gamma": 0.001,
            "kernel": "linear"
        },
        {
            "C": 1.665239691095876,
            "gamma": "scale",
            "kernel": "poly"
        },
        {
            "C": 0.947216090547421,
            "gamma": "auto",
            "kernel": "sigmoid"
        },
        {
            "C": 1.0409549591024096,
            "gamma": 0.001,
            "kernel": "poly"
        },
        {
            "C": 1.4412653094518335,
            "gamma": "auto",
            "kernel": "rbf"
        },
        {
            "C": 1.0747464588980213,
            "gamma": "scale",
            "kernel": "sigmoid"
        },
        {
            "C": 0.21181521437558426,
            "gamma": 0.001,
            "kernel": "poly"
        },
        {
            "C": 1.5484673788684333,
            "gamma": 0.01,
            "kernel": "poly"
        },
        {
            "C": 0.2704363468109041,
            "gamma": 0.01,
            "kernel": "rbf"
        },
        {
            "C": 0.29934973436736634,
            "gamma": "scale",
            "kernel": "linear"
        },
        {
            "C": 0.7729779622517239,
            "gamma": 0.01,
            "kernel": "rbf"
        },
        {
            "C": 0.8998999798224552,
            "gamma": "scale",
            "kernel": "rbf"
        },
        {
            "C": 1.3952623918545297,
            "gamma": "auto",
            "kernel": "rbf"
        },
        {
            "C": 1.3335334308913354,
            "gamma": 0.001,
            "kernel": "poly"
        },
        {
            "C": 0.71630433393905,
            "gamma": "scale",
            "kernel": "poly"
        },
        {
            "C": 1.2156613374309355,
            "gamma": 0.01,
            "kernel": "rbf"
        },
        {
            "C": 0.07685085294546945,
            "gamma": 0.001,
            "kernel": "linear"
        },
        {
            "C": 1.9178985372490407,
            "gamma": 0.01,
            "kernel": "sigmoid"
        },
        {
            "C": 1.9905991353557753,
            "gamma": 0.01,
            "kernel": "linear"
        },
        {
            "C": 0.8287371764527376,
            "gamma": 0.01,
            "kernel": "sigmoid"
        },
        {
            "C": 1.2470202022637364,
            "gamma": 0.1,
            "kernel": "rbf"
        },
        {
            "C": 1.3126591789305468,
            "gamma": "auto",
            "kernel": "rbf"
        },
        {
            "C": 0.393164723360107,
            "gamma": "scale",
            "kernel": "sigmoid"
        },
        {
            "C": 1.6419864596958702,
            "gamma": "scale",
            "kernel": "rbf"
        },
        {
            "C": 1.6758898149976078,
            "gamma": 0.0001,
            "kernel": "linear"
        },
        {
            "C": 1.9529189300267915,
            "gamma": 0.0001,
            "kernel": "poly"
        },
        {
            "C": 1.9535221763806743,
            "gamma": 0.1,
            "kernel": "rbf"
        },
        {
            "C": 0.039975330817517474,
            "gamma": 0.0001,
            "kernel": "poly"
        },
        {
            "C": 1.959173457625457,
            "gamma": 0.001,
            "kernel": "poly"
        },
        {
            "C": 1.3773223656115408,
            "gamma": 0.001,
            "kernel": "poly"
        },
        {
            "C": 0.12829499269756872,
            "gamma": 0.0001,
            "kernel": "poly"
        },
        {
            "C": 1.1332029084131503,
            "gamma": "auto",
            "kernel": "poly"
        },
        {
            "C": 1.0464961069333993,
            "gamma": "auto",
            "kernel": "poly"
        },
        {
            "C": 1.1518929911123585,
            "gamma": 0.0001,
            "kernel": "poly"
        },
        {
            "C": 0.6371379049026473,
            "gamma": 0.001,
            "kernel": "poly"
        }
    ],
    "mean_test_score": [
        0.7049487051446559,
        0.53536911436572,
        0.7177493473575091,
        0.7056617131154277,
        0.5328830679569919,
        0.7138372850072375,
        0.7113531348963041,
        0.6982004133929192,
        0.6942940399360317,
        0.609324728355341,
        0.5328830679569919,
        0.6441635114378361,
        0.5666561316789188,
        0.5328830679569919,
        0.5421256234078999,
        0.624606360182803,
        0.7053121622219554,
        0.6537663634697194,
        0.7013937788790351,
        0.644164143537101,
        0.5328830679569919,
        0.6726079783569212,
        0.6651447823366181,
        0.6843410049114113,
        0.656966049948484,
        0.7109953667123885,
        0.6430984241765326,
        0.7262776306391155,
        0.6416743045327837,
        0.6246120490761868,
        0.7141931568933585,
        0.7099264868554956,
        0.5328830679569919,
        0.7333792658799136,
        0.5328830679569919,
        0.5328830679569919,
        0.5328830679569919,
        0.5328830679569919,
        0.5328830679569919,
        0.5328830679569919,
        0.5328830679569919,
        0.5328830679569919
    ],
    "std_test_score": [
        0.008602072822208097,
        0.004525993172461118,
        0.014945362343672903,
        0.011085398322631477,
        0.0005634114599356099,
        0.011357844398119732,
        0.016664128550753655,
        0.01678865040897579,
        0.022279796334419726,
        0.019292292022403092,
        0.0005634114599356099,
        0.02482228899256667,
        0.010627404992329077,
        0.0005634114599356099,
        0.004584738630136801,
        0.022416205521466746,
        0.018070080508212065,
        0.021470733893834196,
        0.011383194742094508,
        0.025017686996550634,
        0.0005634114599356099,
        0.024031932689089902,
        0.023062296554223392,
        0.02201901259444144,
        0.020918095363066266,
        0.013524116658572952,
        0.022594991038797137,
        0.01557740837125739,
        0.022661361961708485,
        0.01799369544379346,
        0.011426637283545357,
        0.011444410219375239,
        0.0005634114599356099,
        0.011868025798569055,
        0.0005634114599356099,
        0.0005634114599356099,
        0.0005634114599356099,
        0.0005634114599356099,
        0.0005634114599356099,
        0.0005634114599356099,
        0.0005634114599356099,
        0.0005634114599356099
    ],
    "rank_test_score": [
        32,
        14,
        40,
        34,
        1,
        38,
        37,
        30,
        29,
        17,
        1,
        22,
        16,
        1,
        15,
        18,
        33,
        24,
        31,
        23,
        1,
        27,
        26,
        28,
        25,
        36,
        21,
        41,
        20,
        19,
        39,
        35,
        1,
        42,
        1,
        1,
        1,
        1,
        1,
        1,
        1,
        1
    ]
}